{"nodes": [{"id": "packages_tools_src_index_ts", "label": "index.ts", "file_type": "code", "source_file": "packages/tools/src/index.ts", "source_location": "L1"}, {"id": "index_withdataplanealiases", "label": "withDataPlaneAliases()", "file_type": "code", "source_file": "packages/tools/src/index.ts", "source_location": "L504"}, {"id": "index_getruntimetools", "label": "getRuntimeTools()", "file_type": "code", "source_file": "packages/tools/src/index.ts", "source_location": "L1393"}, {"id": "index_listtooldefinitions", "label": "listToolDefinitions()", "file_type": "code", "source_file": "packages/tools/src/index.ts", "source_location": "L1397"}], "edges": [{"source": "packages_tools_src_index_ts", "target": "types", "relation": "imports_from", "confidence": "EXTRACTED", "source_file": "packages/tools/src/index.ts", "source_location": "L1", "weight": 1.0}, {"source": "packages_tools_src_index_ts", "target": "packages_tools_src_sheets_client_ts", "relation": "imports_from", "confidence": "EXTRACTED", "source_file": "packages/tools/src/index.ts", "source_location": "L2", "weight": 1.0}, {"source": "packages_tools_src_index_ts", "target": "packages_tools_src_email_index_ts", "relation": "imports_from", "confidence": "EXTRACTED", "source_file": "packages/tools/src/index.ts", "source_location": "L3", "weight": 1.0}, {"source": "packages_tools_src_index_ts", "target": "packages_tools_src_notifications_index_ts", "relation": "imports_from", "confidence": "EXTRACTED", "source_file": "packages/tools/src/index.ts", "source_location": "L4", "weight": 1.0}, {"source": "packages_tools_src_index_ts", "target": "packages_tools_src_ocr_invoice_parser_ts", "relation": "imports_from", "confidence": "EXTRACTED", "source_file": "packages/tools/src/index.ts", "source_location": "L5", "weight": 1.0}, {"source": "packages_tools_src_index_ts", "target": "packages_tools_src_bank_statement_parser_ts", "relation": "imports_from", "confidence": "EXTRACTED", "source_file": "packages/tools/src/index.ts", "source_location": "L11", "weight": 1.0}, {"source": "packages_tools_src_index_ts", "target": "packages_tools_src_documents_pdf_generator_ts", "relation": "imports_from", "confidence": "EXTRACTED", "source_file": "packages/tools/src/index.ts", "source_location": "L12", "weight": 1.0}, {"source": "packages_tools_src_index_ts", "target": "packages_tools_src_platform_health_ts", "relation": "imports_from", "confidence": "EXTRACTED", "source_file": "packages/tools/src/index.ts", "source_location": "L13", "weight": 1.0}, {"source": "packages_tools_src_index_ts", "target": "index_withdataplanealiases", "relation": "contains", "confidence": "EXTRACTED", "source_file": "packages/tools/src/index.ts", "source_location": "L504", "weight": 1.0}, {"source": "packages_tools_src_index_ts", "target": "index_getruntimetools", "relation": "contains", "confidence": "EXTRACTED", "source_file": "packages/tools/src/index.ts", "source_location": "L1393", "weight": 1.0}, {"source": "packages_tools_src_index_ts", "target": "index_listtooldefinitions", "relation": "contains", "confidence": "EXTRACTED", "source_file": "packages/tools/src/index.ts", "source_location": "L1397", "weight": 1.0}], "raw_calls": [{"caller_nid": "index_withdataplanealiases", "callee": "startsWith", "source_file": "packages/tools/src/index.ts", "source_location": "L507"}, {"caller_nid": "index_withdataplanealiases", "callee": "push", "source_file": "packages/tools/src/index.ts", "source_location": "L508"}, {"caller_nid": "index_withdataplanealiases", "callee": "slice", "source_file": "packages/tools/src/index.ts", "source_location": "L508"}]}